spatialdata_plot/__init__.py
spatialdata_plot/_accessor.py
spatialdata_plot/_logging.py
spatialdata_plot/pl/__init__.py
spatialdata_plot/pl/basic.py
spatialdata_plot/pl/render.py
spatialdata_plot/pl/render_params.py
spatialdata_plot/pl/utils.py
spatialdata_plot-0.2.14.dist-info/METADATA
spatialdata_plot-0.2.14.dist-info/WHEEL
spatialdata_plot-0.2.14.dist-info/licenses/LICENSE
spatialdata_plot-0.2.14.dist-info/RECORD
