Metadata-Version: 2.4
Name: spatialdata-plot
Version: 0.2.14
Summary: Static plotting for spatial data.
Project-URL: Documentation, https://spatialdata.scverse.org/projects/plot/en/latest/index.html
Project-URL: Source, https://github.com/scverse/spatialdata-plot.git
Project-URL: Home-page, https://github.com/scverse/spatialdata-plot.git
Author: scverse
Maintainer-email: Tim Treis <tim.treis@helmholtz-munich.de>
License: BSD 3-Clause License
License-File: LICENSE
Requires-Python: >=3.11
Requires-Dist: matplotlib
Requires-Dist: matplotlib-scalebar
Requires-Dist: scanpy
Requires-Dist: scikit-learn
Requires-Dist: spatialdata>=0.3.0
Provides-Extra: dev
Requires-Dist: ipykernel; extra == 'dev'
Requires-Dist: ipywidgets; extra == 'dev'
Requires-Dist: jupyterlab; extra == 'dev'
Requires-Dist: jupytext; extra == 'dev'
Requires-Dist: notebook; extra == 'dev'
Requires-Dist: pooch; extra == 'dev'
Requires-Dist: pre-commit; extra == 'dev'
Requires-Dist: pytest; extra == 'dev'
Requires-Dist: pytest-cov; extra == 'dev'
Requires-Dist: ruff; extra == 'dev'
Provides-Extra: docs
Requires-Dist: ipython>=8.6.0; extra == 'docs'
Requires-Dist: myst-nb; extra == 'docs'
Requires-Dist: sphinx-autodoc-typehints; extra == 'docs'
Requires-Dist: sphinx-book-theme>=1.0.0; extra == 'docs'
Requires-Dist: sphinx-copybutton; extra == 'docs'
Requires-Dist: sphinx-design; extra == 'docs'
Requires-Dist: sphinx-rtd-theme; extra == 'docs'
Requires-Dist: sphinx>=4.5; extra == 'docs'
Requires-Dist: sphinxcontrib-bibtex>=1.0.0; extra == 'docs'
Provides-Extra: test
Requires-Dist: pooch; extra == 'test'
Requires-Dist: pytest; extra == 'test'
Requires-Dist: pytest-cov; extra == 'test'
Requires-Dist: pytest-xdist; extra == 'test'
